fant_sizer/__init__.py
fant_sizer/fant_sizer.py
fant_sizer-0.7.dist-info/DESCRIPTION.rst
fant_sizer-0.7.dist-info/METADATA
fant_sizer-0.7.dist-info/RECORD
fant_sizer-0.7.dist-info/WHEEL
fant_sizer-0.7.dist-info/entry_points.txt
fant_sizer-0.7.dist-info/metadata.json
fant_sizer-0.7.dist-info/top_level.txt
tests/__init__.py
tests/conftest.py
tests/test_fant_sizer.py
