Metadata-Version: 2.0
Name: fant-sizer
Version: 0.7
Summary: fant_sizer command-line file-information
Home-page: https://github.com/ripiuk/fant_sizer
Author: Rypiuk Oleksandr
Author-email: ripiuk96@gmail.com
License: MIT
Keywords: file command-line information size tool recursively
Platform: UNKNOWN
Classifier: Topic :: Utilities
Classifier: Environment :: Console
Classifier: Natural Language :: English
Classifier: License :: OSI Approved :: MIT License
Classifier: Intended Audience :: Developers
Classifier: Intended Audience :: Information Technology
Classifier: Development Status :: 5 - Production/Stable
Classifier: Programming Language :: Python :: 3.6
